{"computation_definitions":"<b>\uc601   \uc5ed</b>: \ud658\uacbd<br> <b>\ud558\uc704\uc601\uc5ed</b>: \uc548\uc804","indicator_name_sub":"\uad50\ud1b5\uc0ac\uace0 \ubc1c\uc0dd \uac74\uc218","indicator_definition":"\uad50\ud1b5\uc0ac\uace0\ub780 \ub3c4\ub85c\uad50\ud1b5\ubc95 \uc81c2\uc870\uc5d0 \uaddc\uc815\ud558\ub294 \ub3c4\ub85c\uc5d0\uc11c \ucc28\uc758 \uad50\ud1b5\uc73c\ub85c \uc778\ud558\uc5ec \ubc1c\uc0dd\ud55c \uc778\uc801\ud53c\ud574\ub97c \uc218\ubc18\ud558\ub294 \uad50\ud1b5\uc0ac\uace0\ub85c \ucc28\uc758 \uad50\ud1b5\uc73c\ub85c \uc778\ud558\uc5ec \uc0ac\ub78c\uc744 \uc0ac\uc0c1\ud55c \uc0ac\uace0 \uc911 \uacbd\ucc30\uc5d0\uc11c \uc811\uc218\ud558\uc5ec \ucc98\ub9ac\ud55c \uc0ac\uace0\ub97c \uc758\ubbf8\ud568","indicator_importance":"\uacbd\uc81c\ubc1c\uc804\uc5d0 \ub530\ub77c \uae09\uaca9\ud558\uac8c \uc99d\uac00\ud558\uace0 \uc788\ub294 \uc790\ub3d9\ucc28\ub85c \uc778\ud574 \uc2ec\uac01\ud55c \uc0ac\ud68c\ubb38\uc81c\ub85c \ub300\ub450\ub418\uace0 \uc788\ub294 \uad50\ud1b5\uc0ac\uace0\uc5d0 \ub300\ud558\uc5ec \uad6d\ubbfc\uc5d0\uac8c \uad50\ud1b5\uc0ac\uace0\uc758 \uc2ec\uac01\uc131\uacfc \uc6b0\ub9ac\ub098\ub77c\uac00 \uc120\uc9c4\uad6d\uc73c\ub85c \uc9c4\uc785\ud568\uc5d0 \uc788\uc5b4 \ubc18\ub4dc\uc2dc \uac1c\uc120\uc2dc\ucf1c\uc57c \ud560 \ubb38\uc81c\uc784\uc744 \uc778\uc2dd\uc2dc\ucf1c\uc90c","computation_calculations":"\uadf8 \ud574 \uacbd\ucc30\uccad\uc5d0 \uc811\uc218\ub41c \uad50\ud1b5\uc0ac\uace0 \ubc1c\uc0dd\uac74\uc218","statistics_name":"\uacbd\ucc30\uccad(\uad50\ud1b5\uc0ac\uace0\ud1b5\uacc4), \uad6d\ud1a0\uad50\ud1b5\ubd80(\uc790\ub3d9\ucc28\ub4f1\ub85d\ub300\uc218)<br> https://kosis.kr/statHtml/statHtml.do?orgId=101&tblId=DT_1YL21051&conn_path=I2","computation_units":"\uac74","computation_coverage":"\uc2dc\uad70\uad6c","data_preparation_year":"2005\ub144 ~ 2020\ub144","data_generation_cycle":"1\ub144","update_cycle":"\uc775\ub144 7\uc6d4","national_metadata_updated_date":"2022-12-13","national_data_updated_date":"2022-12-13","national_metadata_update_url_text":"2022-12-13: see changes on GitHub","national_metadata_update_url":"https://github.com/karajjang/data/commit/6ad594abea59ebc0a3fd804429691ee421bbfed7","national_data_update_url_text":"2022-12-13: see changes on GitHub","national_data_update_url":"https://github.com/karajjang/data/commit/673811e384b1f3a9de3fd1eee7cb0bb83e00267f","indicator":"11.2.5","target_id":"11.2","sdg_goal":"11","reporting_status":"complete","data_non_statistical":false,"graph_type":"line","indicator_sort_order":"11-02-05","indicator_name":"global_indicators.11-2-5-title","graph_title":"global_indicators.11-2-5-title"}